k3math/__init__.py
k3math/mth.py
k3math/synopsis.py
k3math-0.1.6.dist-info/licenses/LICENSE
k3math-0.1.6.dist-info/METADATA
k3math-0.1.6.dist-info/WHEEL
k3math-0.1.6.dist-info/top_level.txt
k3math-0.1.6.dist-info/RECORD
